docs/gen_tree.py
site/gen_tree.py
tests/__init__.py
tests/conftest.py
tests/test_web_base.py
web_base/__init__.py
web_base/config.py
web_base-0.1.5.dist-info/METADATA
web_base-0.1.5.dist-info/WHEEL
web_base-0.1.5.dist-info/top_level.txt
web_base-0.1.5.dist-info/RECORD
