Metadata-Version: 2.1
Name: web-base
Version: 0.1.5
Summary: Base para manipulação web com selenium.
Author-email: MatheusLPolidoro <mattpolidoro4@gmail.com>
Project-URL: Documentation, https://matheuslpolidoro.github.io/web-base/
Project-URL: Source Code, https://github.com/MatheusLPolidoro/web-base
Project-URL: Bug Tracker, https://github.com/MatheusLPolidoro/web-base/issues
Requires-Python: >=3.8
Requires-Dist: selenium==4.35.0
